{
  "collectionName": "components_address_addresses",
  "info": {
    "displayName": "Address",
    "icon": "pinMap"
  },
  "options": {},
  "attributes": {
    "streetDetails": {
      "type": "string"
    },
    "city": {
      "type": "string"
    },
    "state": {
      "type": "string"
    },
    "ZIP": {
      "type": "string"
    },
    "country": {
      "type": "string"
    },
    "mapLink": {
      "type": "text"
    },
    "email": {
      "type": "email"
    },
    "phone": {
      "type": "string"
    }
  }
}
